pyvisca/__init__.py
pyvisca/visca.py
pyvisca-0.1.6.dist-info/METADATA
pyvisca-0.1.6.dist-info/WHEEL
pyvisca-0.1.6.dist-info/licenses/LICENSE
pyvisca-0.1.6.dist-info/RECORD
