Metadata-Version: 2.4
Name: pyvisca
Version: 0.1.6
Summary: A Python module for controlling PTZ cameras running on Sony VISCA protocol via serial USB
Project-URL: Documentation, https://github.com/groaking/pyvisca/blob/master/README.md
Project-URL: Homepage, https://github.com/groaking/pyvisca
Project-URL: Repository, https://github.com/groaking/pyvisca.git
Project-URL: Changelog, https://github.com/groaking/pyvisca/blob/master/CHANGELOG.md
Project-URL: Issues, https://github.com/groaking/pyvisca/issues
Author-email: Samarthya Lykamanuella <93555329+groaking@users.noreply.github.com>
Maintainer-email: Samarthya Lykamanuella <93555329+groaking@users.noreply.github.com>
License:                     GNU GENERAL PUBLIC LICENSE
License-File: LICENSE
Keywords: CCTV,PTZ,Sony,VISCA,camera,control,digital camera,interface,lens,pan tilt zoom,serial,serial monitor
Classifier: Development Status :: 2 - Pre-Alpha
Classifier: Intended Audience :: Developers
Classifier: Intended Audience :: Other Audience
Classifier: License :: OSI Approved :: GNU General Public License v3 (GPLv3)
Classifier: Natural Language :: English
Classifier: Operating System :: OS Independent
Classifier: Programming Language :: Python :: 3
Classifier: Topic :: Multimedia :: Graphics :: Capture :: Digital Camera
Classifier: Topic :: Multimedia :: Video
Classifier: Topic :: System :: Hardware :: Universal Serial Bus (USB)
Classifier: Topic :: System :: Hardware :: Universal Serial Bus (USB) :: Communications Device Class (CDC)
Classifier: Topic :: System :: Hardware :: Universal Serial Bus (USB) :: Miscellaneous
Classifier: Topic :: Utilities
Requires-Python: >=3.8
Requires-Dist: pyserial
